odoo/addons/l10n_ro_stock_account_reception_in_progress/README.rst
odoo/addons/l10n_ro_stock_account_reception_in_progress/__init__.py
odoo/addons/l10n_ro_stock_account_reception_in_progress/__manifest__.py
odoo/addons/l10n_ro_stock_account_reception_in_progress/i18n/l10n_ro_stock_account_reception_in_progress.pot
odoo/addons/l10n_ro_stock_account_reception_in_progress/i18n/ro.po
odoo/addons/l10n_ro_stock_account_reception_in_progress/models/__init__.py
odoo/addons/l10n_ro_stock_account_reception_in_progress/models/account_account.py
odoo/addons/l10n_ro_stock_account_reception_in_progress/models/account_move_line.py
odoo/addons/l10n_ro_stock_account_reception_in_progress/models/product.py
odoo/addons/l10n_ro_stock_account_reception_in_progress/models/purchase_order.py
odoo/addons/l10n_ro_stock_account_reception_in_progress/models/stock_move.py
odoo/addons/l10n_ro_stock_account_reception_in_progress/models/stock_picking.py
odoo/addons/l10n_ro_stock_account_reception_in_progress/readme/CONTRIBUTORS.md
odoo/addons/l10n_ro_stock_account_reception_in_progress/readme/DESCRIPTION.md
odoo/addons/l10n_ro_stock_account_reception_in_progress/static/description/icon.png
odoo/addons/l10n_ro_stock_account_reception_in_progress/static/description/icon.svg
odoo/addons/l10n_ro_stock_account_reception_in_progress/static/description/index.html
odoo/addons/l10n_ro_stock_account_reception_in_progress/tests/__init__.py
odoo/addons/l10n_ro_stock_account_reception_in_progress/tests/test_purchase.py
odoo/addons/l10n_ro_stock_account_reception_in_progress/views/account_account_view.xml
odoo/addons/l10n_ro_stock_account_reception_in_progress/views/purchase_order_view.xml
odoo_addon_l10n_ro_stock_account_reception_in_progress-18.0.0.2.0.dist-info/METADATA
odoo_addon_l10n_ro_stock_account_reception_in_progress-18.0.0.2.0.dist-info/WHEEL
odoo_addon_l10n_ro_stock_account_reception_in_progress-18.0.0.2.0.dist-info/top_level.txt
odoo_addon_l10n_ro_stock_account_reception_in_progress-18.0.0.2.0.dist-info/RECORD
